odoo/addons/web_notify/README.rst
odoo/addons/web_notify/__init__.py
odoo/addons/web_notify/__manifest__.py
odoo/addons/web_notify/i18n/da.po
odoo/addons/web_notify/i18n/de.po
odoo/addons/web_notify/i18n/es.po
odoo/addons/web_notify/i18n/hr.po
odoo/addons/web_notify/i18n/nl_NL.po
odoo/addons/web_notify/i18n/pt_BR.po
odoo/addons/web_notify/i18n/web_notify.pot
odoo/addons/web_notify/models/__init__.py
odoo/addons/web_notify/models/res_users.py
odoo/addons/web_notify/static/description/icon.png
odoo/addons/web_notify/static/description/notifications_screenshot.png
odoo/addons/web_notify/static/src/js/web_client.js
odoo/addons/web_notify/tests/__init__.py
odoo/addons/web_notify/tests/test_res_users.py
odoo/addons/web_notify/views/web_notify.xml
odoo11_addon_web_notify-11.0.1.1.1.dist-info/METADATA
odoo11_addon_web_notify-11.0.1.1.1.dist-info/WHEEL
odoo11_addon_web_notify-11.0.1.1.1.dist-info/top_level.txt
odoo11_addon_web_notify-11.0.1.1.1.dist-info/RECORD
